cacaodocs/__init__.py
cacaodocs/documentation.py
cacaodocs/parser.py
cacaodocs/type_definitions.py
cacaodocs/frontend/build/asset-manifest.json
cacaodocs/frontend/build/bundle.js.LICENSE.txt
cacaodocs/frontend/build/bundle.js.map
cacaodocs/frontend/build/data.js
cacaodocs/frontend/build/index.html
cacaodocs/frontend/build/images/247245c2e4427002df30.js
cacaodocs/frontend/build/static/css/styles.db95c65d.css
cacaodocs/frontend/build/static/css/styles.db95c65d.css.map
cacaodocs-0.1.14.dist-info/LICENSE
cacaodocs-0.1.14.dist-info/METADATA
cacaodocs-0.1.14.dist-info/WHEEL
cacaodocs-0.1.14.dist-info/top_level.txt
cacaodocs-0.1.14.dist-info/RECORD
