Metadata-Version: 2.2
Name: cacaodocs
Version: 0.1.14
Summary: A lightweight Python package to extract API documentation from docstrings.
Home-page: https://github.com/jhd3197/CacaoDocs
Author: Juan Denis
Author-email: juan@vene.co
Classifier: Programming Language :: Python :: 3
Classifier: License :: OSI Approved :: MIT License
Classifier: Operating System :: OS Independent
Requires-Python: >=3.6
License-File: LICENSE
Requires-Dist: Jinja2==3.0.0
Requires-Dist: Markdown==3.7
Requires-Dist: beautifulsoup4==4.12.3
Requires-Dist: Flask==2.0.0
Requires-Dist: PyYAML==6.0.2
Requires-Dist: Werkzeug==2.0.0
Requires-Dist: Flask-Cors==5.0.0
Dynamic: author
Dynamic: author-email
Dynamic: classifier
Dynamic: description
Dynamic: description-content-type
Dynamic: home-page
Dynamic: requires-dist
Dynamic: requires-python
Dynamic: summary
